stepaudio2/__init__.py
stepaudio2/stepaudio2.py
stepaudio2/token2wav.py
stepaudio2/utils.py
stepaudio2/cosyvoice2/__init__.py
stepaudio2/cosyvoice2/flow/__init__.py
stepaudio2/cosyvoice2/flow/decoder_dit.py
stepaudio2/cosyvoice2/flow/flow.py
stepaudio2/cosyvoice2/flow/flow_matching.py
stepaudio2/cosyvoice2/transformer/__init__.py
stepaudio2/cosyvoice2/transformer/attention.py
stepaudio2/cosyvoice2/transformer/embedding.py
stepaudio2/cosyvoice2/transformer/encoder_layer.py
stepaudio2/cosyvoice2/transformer/positionwise_feed_forward.py
stepaudio2/cosyvoice2/transformer/subsampling.py
stepaudio2/cosyvoice2/transformer/upsample_encoder_v2.py
stepaudio2/cosyvoice2/utils/__init__.py
stepaudio2/cosyvoice2/utils/class_utils.py
stepaudio2/cosyvoice2/utils/common.py
stepaudio2/cosyvoice2/utils/mask.py
stepaudio2/flashcosyvoice/__init__.py
stepaudio2/flashcosyvoice/cli.py
stepaudio2/flashcosyvoice/config.py
stepaudio2/flashcosyvoice/cosyvoice2.py
stepaudio2/flashcosyvoice/cosyvoice3.py
stepaudio2/flashcosyvoice/engine/__init__.py
stepaudio2/flashcosyvoice/engine/block_manager.py
stepaudio2/flashcosyvoice/engine/llm_engine.py
stepaudio2/flashcosyvoice/engine/model_runner.py
stepaudio2/flashcosyvoice/engine/scheduler.py
stepaudio2/flashcosyvoice/engine/sequence.py
stepaudio2/flashcosyvoice/modules/__init__.py
stepaudio2/flashcosyvoice/modules/flow.py
stepaudio2/flashcosyvoice/modules/hifigan.py
stepaudio2/flashcosyvoice/modules/qwen2.py
stepaudio2/flashcosyvoice/modules/sampler.py
stepaudio2/flashcosyvoice/modules/flow_components/__init__.py
stepaudio2/flashcosyvoice/modules/flow_components/estimator.py
stepaudio2/flashcosyvoice/modules/flow_components/upsample_encoder.py
stepaudio2/flashcosyvoice/modules/hifigan_components/__init__.py
stepaudio2/flashcosyvoice/modules/hifigan_components/layers.py
stepaudio2/flashcosyvoice/modules/qwen2_components/__init__.py
stepaudio2/flashcosyvoice/modules/qwen2_components/layers.py
stepaudio2/flashcosyvoice/utils/__init__.py
token2wav_cosyvoice_stepaudio2-0.1.3.dist-info/METADATA
token2wav_cosyvoice_stepaudio2-0.1.3.dist-info/WHEEL
token2wav_cosyvoice_stepaudio2-0.1.3.dist-info/top_level.txt
token2wav_cosyvoice_stepaudio2-0.1.3.dist-info/RECORD
